tdta/__init__.py
tdta/__main__.py
tdta/anndata_export.py
tdta/command_line_utils.py
tdta/documentation.py
tdta/git_utils.py
tdta/purl_publish.py
tdta/tdt_export.py
tdta/utils.py
tdta/version_control.py
tdta/resources/annotation_template.md
tdta/resources/taxonomy_template.md
tdta-0.1.5.dist-info/LICENSE
tdta-0.1.5.dist-info/METADATA
tdta-0.1.5.dist-info/WHEEL
tdta-0.1.5.dist-info/entry_points.txt
tdta-0.1.5.dist-info/top_level.txt
tdta-0.1.5.dist-info/RECORD
