Metadata-Version: 2.1
Name: tdta
Version: 0.1.5
Summary: The aim of this project is to provide taxonomy development tools custom actions.
Home-page: https://github.com/brain-bican/taxonomy-development-tools-actions
Author: 
License: Apache-2.0 license
Classifier: Programming Language :: Python :: 3
Classifier: License :: OSI Approved :: GNU General Public License v3 (GPLv3)
Classifier: Operating System :: OS Independent
License-File: LICENSE
Requires-Dist: requests
Requires-Dist: cas-tools
